{"id":"sisi","country":"Egypt","countryCode":"EG","name":"Abdel Fattah el-Sisi","handle":"@AlsisiOfficial","query":"(\"Abdel Fattah el-Sisi\" OR \"el-Sisi\" OR @AlsisiOfficial) -is:retweet","trackerId":"a324b28f-3d2e-461f-bc14-0d438bf54f25","totalMentions":19343,"history":[{"date":"2025-01-01","count":34},{"date":"2025-01-02","count":14},{"date":"2025-01-03","count":21},{"date":"2025-01-04","count":37},{"date":"2025-01-05","count":29},{"date":"2025-01-06","count":29},{"date":"2025-01-07","count":22},{"date":"2025-01-08","count":47},{"date":"2025-01-09","count":42},{"date":"2025-01-10","count":31},{"date":"2025-01-11","count":30},{"date":"2025-01-12","count":26},{"date":"2025-01-13","count":34},{"date":"2025-01-14","count":53},{"date":"2025-01-15","count":58},{"date":"2025-01-16","count":46},{"date":"2025-01-17","count":42},{"date":"2025-01-18","count":30},{"date":"2025-01-19","count":18},{"date":"2025-01-20","count":31},{"date":"2025-01-21","count":56},{"date":"2025-01-22","count":89},{"date":"2025-01-23","count":27},{"date":"2025-01-24","count":31},{"date":"2025-01-25","count":71},{"date":"2025-01-26","count":68},{"date":"2025-01-27","count":77},{"date":"2025-01-28","count":213},{"date":"2025-01-29","count":74},{"date":"2025-01-30","count":53},{"date":"2025-02-01","count":134},{"date":"2025-02-02","count":38},{"date":"2025-02-03","count":48},{"date":"2025-02-04","count":63},{"date":"2025-02-05","count":48},{"date":"2025-02-06","count":25},{"date":"2025-02-07","count":37},{"date":"2025-02-08","count":12},{"date":"2025-02-09","count":30},{"date":"2025-02-10","count":41},{"date":"2025-02-11","count":158},{"date":"2025-02-12","count":141},{"date":"2025-02-13","count":38},{"date":"2025-02-14","count":28},{"date":"2025-02-15","count":57},{"date":"2025-02-16","count":39},{"date":"2025-02-17","count":32},{"date":"2025-02-18","count":39},{"date":"2025-02-19","count":81},{"date":"2025-02-20","count":14},{"date":"2025-02-21","count":29},{"date":"2025-02-22","count":10},{"date":"2025-02-23","count":48},{"date":"2025-02-24","count":41},{"date":"2025-02-25","count":56},{"date":"2025-02-26","count":17},{"date":"2025-02-27","count":17},{"date":"2025-02-28","count":18},{"date":"2025-03-01","count":15},{"date":"2025-03-02","count":25},{"date":"2025-03-03","count":12},{"date":"2025-03-04","count":146},{"date":"2025-03-05","count":54},{"date":"2025-03-06","count":15},{"date":"2025-03-07","count":17},{"date":"2025-03-08","count":11},{"date":"2025-03-09","count":17},{"date":"2025-03-10","count":21},{"date":"2025-03-11","count":22},{"date":"2025-03-12","count":21},{"date":"2025-03-13","count":14},{"date":"2025-03-14","count":6},{"date":"2025-03-15","count":7},{"date":"2025-03-16","count":18},{"date":"2025-03-17","count":25},{"date":"2025-03-18","count":31},{"date":"2025-03-19","count":17},{"date":"2025-03-20","count":90},{"date":"2025-03-21","count":29},{"date":"2025-03-22","count":48},{"date":"2025-03-23","count":42},{"date":"2025-03-24","count":27},{"date":"2025-03-25","count":54},{"date":"2025-03-26","count":71},{"date":"2025-03-27","count":36},{"date":"2025-03-28","count":26},{"date":"2025-03-29","count":10},{"date":"2025-03-30","count":24},{"date":"2025-04-01","count":128},{"date":"2025-04-02","count":42},{"date":"2025-04-03","count":22},{"date":"2025-04-04","count":8},{"date":"2025-04-05","count":19},{"date":"2025-04-06","count":59},{"date":"2025-04-07","count":147},{"date":"2025-04-08","count":64},{"date":"2025-04-09","count":17},{"date":"2025-04-10","count":13},{"date":"2025-04-11","count":11},{"date":"2025-04-12","count":39},{"date":"2025-04-13","count":90},{"date":"2025-04-14","count":69},{"date":"2025-04-15","count":34},{"date":"2025-04-16","count":14},{"date":"2025-04-17","count":16},{"date":"2025-04-18","count":25},{"date":"2025-04-19","count":10},{"date":"2025-04-20","count":20},{"date":"2025-04-21","count":30},{"date":"2025-04-22","count":11},{"date":"2025-04-23","count":71},{"date":"2025-04-24","count":43},{"date":"2025-04-25","count":36},{"date":"2025-04-26","count":14},{"date":"2025-04-27","count":22},{"date":"2025-04-28","count":41},{"date":"2025-04-29","count":24},{"date":"2025-04-30","count":11},{"date":"2025-05-01","count":24},{"date":"2025-05-02","count":11},{"date":"2025-05-03","count":17},{"date":"2025-05-04","count":20},{"date":"2025-05-05","count":21},{"date":"2025-05-06","count":17},{"date":"2025-05-07","count":57},{"date":"2025-05-08","count":70},{"date":"2025-05-09","count":96},{"date":"2025-05-10","count":49},{"date":"2025-05-11","count":12},{"date":"2025-05-12","count":29},{"date":"2025-05-13","count":18},{"date":"2025-05-14","count":21},{"date":"2025-05-15","count":39},{"date":"2025-05-16","count":72},{"date":"2025-05-17","count":123},{"date":"2025-05-18","count":56},{"date":"2025-05-19","count":31},{"date":"2025-05-20","count":22},{"date":"2025-05-21","count":30},{"date":"2025-05-22","count":21},{"date":"2025-05-23","count":18},{"date":"2025-05-24","count":15},{"date":"2025-05-25","count":16},{"date":"2025-05-26","count":20},{"date":"2025-05-27","count":18},{"date":"2025-05-28","count":21},{"date":"2025-05-29","count":37},{"date":"2025-05-30","count":23},{"date":"2025-06-01","count":16},{"date":"2025-06-02","count":61},{"date":"2025-06-03","count":32},{"date":"2025-06-04","count":49},{"date":"2025-06-05","count":27},{"date":"2025-06-06","count":21},{"date":"2025-06-07","count":17},{"date":"2025-06-08","count":19},{"date":"2025-06-09","count":14},{"date":"2025-06-10","count":11},{"date":"2025-06-11","count":26},{"date":"2025-06-12","count":79},{"date":"2025-06-13","count":59},{"date":"2025-06-14","count":86},{"date":"2025-06-15","count":57},{"date":"2025-06-16","count":35},{"date":"2025-06-17","count":33},{"date":"2025-06-18","count":12},{"date":"2025-06-19","count":15},{"date":"2025-06-20","count":22},{"date":"2025-06-21","count":29},{"date":"2025-06-22","count":17},{"date":"2025-06-23","count":24},{"date":"2025-06-24","count":24},{"date":"2025-06-25","count":23},{"date":"2025-06-26","count":18},{"date":"2025-06-27","count":26},{"date":"2025-06-28","count":18},{"date":"2025-06-29","count":19},{"date":"2025-06-30","count":108},{"date":"2025-07-01","count":26},{"date":"2025-07-02","count":25},{"date":"2025-07-03","count":13},{"date":"2025-07-04","count":26},{"date":"2025-07-05","count":25},{"date":"2025-07-06","count":60},{"date":"2025-07-07","count":79},{"date":"2025-07-08","count":38},{"date":"2025-07-09","count":6},{"date":"2025-07-10","count":29},{"date":"2025-07-11","count":14},{"date":"2025-07-12","count":27},{"date":"2025-07-13","count":34},{"date":"2025-07-14","count":16},{"date":"2025-07-15","count":12},{"date":"2025-07-16","count":12},{"date":"2025-07-17","count":22},{"date":"2025-07-18","count":15},{"date":"2025-07-19","count":32},{"date":"2025-07-20","count":47},{"date":"2025-07-21","count":45},{"date":"2025-07-22","count":69},{"date":"2025-07-23","count":52},{"date":"2025-07-24","count":38},{"date":"2025-07-25","count":31},{"date":"2025-07-26","count":56},{"date":"2025-07-27","count":84},{"date":"2025-07-28","count":33},{"date":"2025-07-29","count":29},{"date":"2025-07-30","count":29},{"date":"2025-08-01","count":22},{"date":"2025-08-02","count":15},{"date":"2025-08-03","count":27},{"date":"2025-08-04","count":26},{"date":"2025-08-05","count":140},{"date":"2025-08-06","count":68},{"date":"2025-08-07","count":41},{"date":"2025-08-08","count":32},{"date":"2025-08-09","count":57},{"date":"2025-08-10","count":32},{"date":"2025-08-11","count":94},{"date":"2025-08-12","count":138},{"date":"2025-08-13","count":87},{"date":"2025-08-14","count":46},{"date":"2025-08-15","count":20},{"date":"2025-08-16","count":12},{"date":"2025-08-17","count":30},{"date":"2025-08-18","count":35},{"date":"2025-08-19","count":21},{"date":"2025-08-20","count":96},{"date":"2025-08-21","count":73},{"date":"2025-08-22","count":24},{"date":"2025-08-23","count":13},{"date":"2025-08-24","count":18},{"date":"2025-08-25","count":36},{"date":"2025-08-26","count":38},{"date":"2025-08-27","count":8},{"date":"2025-08-28","count":15},{"date":"2025-08-29","count":8},{"date":"2025-08-30","count":19},{"date":"2025-09-01","count":22},{"date":"2025-09-02","count":19},{"date":"2025-09-03","count":25},{"date":"2025-09-04","count":8},{"date":"2025-09-05","count":6},{"date":"2025-09-06","count":8},{"date":"2025-09-07","count":25},{"date":"2025-09-08","count":41},{"date":"2025-09-09","count":73},{"date":"2025-09-10","count":33},{"date":"2025-09-11","count":35},{"date":"2025-09-12","count":25},{"date":"2025-09-13","count":24},{"date":"2025-09-14","count":34},{"date":"2025-09-15","count":147},{"date":"2025-09-16","count":58},{"date":"2025-09-17","count":63},{"date":"2025-09-18","count":44},{"date":"2025-09-19","count":27},{"date":"2025-09-20","count":32},{"date":"2025-09-21","count":146},{"date":"2025-09-22","count":71},{"date":"2025-09-23","count":63},{"date":"2025-09-24","count":27},{"date":"2025-09-25","count":22},{"date":"2025-09-26","count":24},{"date":"2025-09-27","count":33},{"date":"2025-09-28","count":34},{"date":"2025-09-29","count":75},{"date":"2025-09-30","count":41},{"date":"2025-10-01","count":22},{"date":"2025-10-02","count":9},{"date":"2025-10-03","count":12},{"date":"2025-10-04","count":19},{"date":"2025-10-05","count":19},{"date":"2025-10-06","count":54},{"date":"2025-10-07","count":22},{"date":"2025-10-08","count":117},{"date":"2025-10-09","count":175},{"date":"2025-10-10","count":48},{"date":"2025-10-11","count":162},{"date":"2025-10-12","count":422},{"date":"2025-10-13","count":1158},{"date":"2025-10-14","count":160},{"date":"2025-10-15","count":59},{"date":"2025-10-16","count":32},{"date":"2025-10-17","count":46},{"date":"2025-10-18","count":57},{"date":"2025-10-19","count":39},{"date":"2025-10-20","count":34},{"date":"2025-10-21","count":121},{"date":"2025-10-22","count":86},{"date":"2025-10-23","count":28},{"date":"2025-10-24","count":55},{"date":"2025-10-25","count":40},{"date":"2025-10-26","count":43},{"date":"2025-10-27","count":45},{"date":"2025-10-28","count":17},{"date":"2025-10-29","count":89},{"date":"2025-10-30","count":78},{"date":"2025-11-01","count":143},{"date":"2025-11-02","count":77},{"date":"2025-11-03","count":40},{"date":"2025-11-04","count":21},{"date":"2025-11-05","count":33},{"date":"2025-11-06","count":13},{"date":"2025-11-07","count":9},{"date":"2025-11-08","count":9},{"date":"2025-11-09","count":15},{"date":"2025-11-10","count":33},{"date":"2025-11-11","count":15},{"date":"2025-11-12","count":22},{"date":"2025-11-13","count":16},{"date":"2025-11-14","count":10},{"date":"2025-11-15","count":12},{"date":"2025-11-16","count":19},{"date":"2025-11-17","count":20},{"date":"2025-11-18","count":29},{"date":"2025-11-19","count":81},{"date":"2025-11-20","count":39},{"date":"2025-11-21","count":24},{"date":"2025-11-22","count":10},{"date":"2025-11-23","count":11},{"date":"2025-11-24","count":25},{"date":"2025-11-25","count":19},{"date":"2025-11-26","count":22},{"date":"2025-11-27","count":12},{"date":"2025-11-28","count":7},{"date":"2025-11-29","count":12},{"date":"2025-11-30","count":18},{"date":"2025-12-01","count":27},{"date":"2025-12-02","count":8},{"date":"2025-12-03","count":21},{"date":"2025-12-04","count":7},{"date":"2025-12-05","count":6},{"date":"2025-12-06","count":8},{"date":"2025-12-07","count":25},{"date":"2025-12-08","count":29},{"date":"2025-12-09","count":10},{"date":"2025-12-10","count":18},{"date":"2025-12-11","count":11},{"date":"2025-12-12","count":15},{"date":"2025-12-13","count":9},{"date":"2025-12-14","count":6},{"date":"2025-12-15","count":9},{"date":"2025-12-16","count":14},{"date":"2025-12-17","count":28},{"date":"2025-12-18","count":38},{"date":"2025-12-19","count":54},{"date":"2025-12-20","count":70},{"date":"2025-12-21","count":52},{"date":"2025-12-22","count":26},{"date":"2025-12-23","count":9},{"date":"2025-12-24","count":15},{"date":"2025-12-25","count":5},{"date":"2025-12-26","count":21},{"date":"2025-12-27","count":32},{"date":"2025-12-28","count":34},{"date":"2025-12-29","count":22},{"date":"2025-12-30","count":13},{"date":"2026-01-01","count":20},{"date":"2026-01-02","count":16},{"date":"2026-01-03","count":46},{"date":"2026-01-04","count":38},{"date":"2026-01-05","count":39},{"date":"2026-01-06","count":23},{"date":"2026-01-07","count":13},{"date":"2026-01-08","count":3},{"date":"2026-01-09","count":8},{"date":"2026-01-10","count":15},{"date":"2026-01-11","count":21},{"date":"2026-01-12","count":5},{"date":"2026-01-13","count":90},{"date":"2026-01-14","count":107},{"date":"2026-01-15","count":27},{"date":"2026-01-16","count":147},{"date":"2026-01-17","count":91},{"date":"2026-01-18","count":29},{"date":"2026-01-19","count":34},{"date":"2026-01-20","count":74},{"date":"2026-01-21","count":258},{"date":"2026-01-22","count":44},{"date":"2026-01-23","count":33},{"date":"2026-01-24","count":33},{"date":"2026-01-25","count":12},{"date":"2026-01-26","count":6},{"date":"2026-01-27","count":10},{"date":"2026-01-28","count":9},{"date":"2026-01-29","count":74},{"date":"2026-01-30","count":58},{"date":"2026-02-01","count":55},{"date":"2026-02-02","count":28},{"date":"2026-02-03","count":137},{"date":"2026-02-04","count":90},{"date":"2026-02-05","count":25},{"date":"2026-02-06","count":11},{"date":"2026-02-07","count":37},{"date":"2026-02-08","count":55},{"date":"2026-02-09","count":71},{"date":"2026-02-10","count":43},{"date":"2026-02-11","count":34},{"date":"2026-02-12","count":27},{"date":"2026-02-13","count":9},{"date":"2026-02-14","count":6},{"date":"2026-02-15","count":12},{"date":"2026-02-16","count":17},{"date":"2026-02-17","count":12},{"date":"2026-02-18","count":10},{"date":"2026-02-19","count":22},{"date":"2026-02-20","count":14},{"date":"2026-02-21","count":24},{"date":"2026-02-22","count":32},{"date":"2026-02-23","count":87},{"date":"2026-02-24","count":13},{"date":"2026-02-25","count":21},{"date":"2026-02-26","count":15},{"date":"2026-02-27","count":12},{"date":"2026-02-28","count":50},{"date":"2026-03-01","count":29},{"date":"2026-03-02","count":35},{"date":"2026-03-03","count":18},{"date":"2026-03-04","count":19},{"date":"2026-03-05","count":23},{"date":"2026-03-06","count":40},{"date":"2026-03-07","count":19},{"date":"2026-03-08","count":25},{"date":"2026-03-09","count":43},{"date":"2026-03-10","count":18},{"date":"2026-03-11","count":9},{"date":"2026-03-12","count":20},{"date":"2026-03-13","count":28},{"date":"2026-03-14","count":28},{"date":"2026-03-15","count":50},{"date":"2026-03-16","count":47},{"date":"2026-03-17","count":13},{"date":"2026-03-18","count":34},{"date":"2026-03-19","count":47},{"date":"2026-03-20","count":51},{"date":"2026-03-21","count":80},{"date":"2026-03-22","count":17},{"date":"2026-03-23","count":16},{"date":"2026-03-24","count":21},{"date":"2026-03-25","count":23},{"date":"2026-03-26","count":20},{"date":"2026-03-27","count":17},{"date":"2026-03-28","count":31},{"date":"2026-03-29","count":224},{"date":"2026-03-30","count":113},{"date":"2026-04-01","count":17},{"date":"2026-04-02","count":17},{"date":"2026-04-03","count":21},{"date":"2026-04-04","count":46},{"date":"2026-04-05","count":8},{"date":"2026-04-06","count":5},{"date":"2026-04-07","count":3},{"date":"2026-04-08","count":16},{"date":"2026-04-09","count":5},{"date":"2026-04-10","count":5},{"date":"2026-04-11","count":2},{"date":"2026-04-12","count":2},{"date":"2026-04-13","count":4},{"date":"2026-04-14","count":3},{"date":"2026-04-15","count":267},{"date":"2026-04-16","count":214},{"date":"2026-04-17","count":145},{"date":"2026-04-18","count":188},{"date":"2026-04-19","count":150},{"date":"2026-04-20","count":274},{"date":"2026-04-21","count":175},{"date":"2026-04-22","count":79},{"date":"2026-04-23","count":131},{"date":"2026-04-24","count":213},{"date":"2026-04-25","count":96}],"engagement":{"totalLikes":118342,"totalRTs":17067,"totalImpressions":9643816,"totalReplies":21187,"totalQuotes":0,"totalBookmarks":0,"engagementRate":1.62,"tweetsPosted":12,"originalTweets":12,"retweetsSent":0,"repliesSent":0,"avgLikesPerTweet":9862,"avgRTsPerTweet":1422},"topRetweeted":[],"topMentioned":[],"topHashtags":[],"tracker":{"snapshots":[{"timestamp":1619342280,"date":"2021-04-25","followers":4974876,"following":0,"tweets":2844,"lists":1887,"mentionsReceived":1427223,"retweetsReceived":810470,"followersFollowing":0},{"timestamp":1621934280,"date":"2021-05-25","followers":5086240,"following":0,"tweets":2860,"lists":1898,"mentionsReceived":1479219,"retweetsReceived":830157,"followersFollowing":0},{"timestamp":1624526280,"date":"2021-06-24","followers":5156447,"following":0,"tweets":2862,"lists":1900,"mentionsReceived":1513544,"retweetsReceived":836187,"followersFollowing":0},{"timestamp":1627118280,"date":"2021-07-24","followers":5209847,"following":0,"tweets":2868,"lists":1910,"mentionsReceived":1565936,"retweetsReceived":844922,"followersFollowing":0},{"timestamp":1629710280,"date":"2021-08-23","followers":5270650,"following":0,"tweets":2879,"lists":1915,"mentionsReceived":1637223,"retweetsReceived":854259,"followersFollowing":0},{"timestamp":1632302280,"date":"2021-09-22","followers":5332320,"following":0,"tweets":2886,"lists":1924,"mentionsReceived":1698950,"retweetsReceived":861854,"followersFollowing":0},{"timestamp":1634894280,"date":"2021-10-22","followers":5385105,"following":0,"tweets":2891,"lists":1924,"mentionsReceived":1741695,"retweetsReceived":866654,"followersFollowing":0},{"timestamp":1637486280,"date":"2021-11-21","followers":5442804,"following":0,"tweets":2899,"lists":1918,"mentionsReceived":1782678,"retweetsReceived":875062,"followersFollowing":0},{"timestamp":1640078280,"date":"2021-12-21","followers":5477340,"following":0,"tweets":2908,"lists":0,"mentionsReceived":1818479,"retweetsReceived":879923,"followersFollowing":0},{"timestamp":1642670280,"date":"2022-01-20","followers":5511098,"following":0,"tweets":2909,"lists":1935,"mentionsReceived":1849423,"retweetsReceived":881818,"followersFollowing":0},{"timestamp":1645262280,"date":"2022-02-19","followers":5553131,"following":0,"tweets":2916,"lists":1972,"mentionsReceived":1879970,"retweetsReceived":896943,"followersFollowing":0},{"timestamp":1647854280,"date":"2022-03-21","followers":5592096,"following":0,"tweets":2919,"lists":1981,"mentionsReceived":1902896,"retweetsReceived":902803,"followersFollowing":0},{"timestamp":1650446280,"date":"2022-04-20","followers":5640690,"following":0,"tweets":2924,"lists":1994,"mentionsReceived":1929382,"retweetsReceived":907400,"followersFollowing":0},{"timestamp":1653038280,"date":"2022-05-20","followers":5725145,"following":0,"tweets":2932,"lists":2014,"mentionsReceived":1964803,"retweetsReceived":917473,"followersFollowing":0},{"timestamp":1655630280,"date":"2022-06-19","followers":5757987,"following":0,"tweets":2937,"lists":2014,"mentionsReceived":1987230,"retweetsReceived":919426,"followersFollowing":0},{"timestamp":1658222280,"date":"2022-07-19","followers":5792557,"following":0,"tweets":2941,"lists":2028,"mentionsReceived":2019667,"retweetsReceived":922632,"followersFollowing":0},{"timestamp":1660814280,"date":"2022-08-18","followers":5853741,"following":0,"tweets":2946,"lists":2029,"mentionsReceived":2044915,"retweetsReceived":925792,"followersFollowing":0},{"timestamp":1663406280,"date":"2022-09-17","followers":5777835,"following":0,"tweets":2948,"lists":0,"mentionsReceived":2066234,"retweetsReceived":926935,"followersFollowing":0},{"timestamp":1665998280,"date":"2022-10-17","followers":5705319,"following":0,"tweets":2953,"lists":2042,"mentionsReceived":2083648,"retweetsReceived":931345,"followersFollowing":0},{"timestamp":1668590280,"date":"2022-11-16","followers":5787783,"following":0,"tweets":2956,"lists":2052,"mentionsReceived":2118503,"retweetsReceived":934557,"followersFollowing":0},{"timestamp":1671182280,"date":"2022-12-16","followers":5833192,"following":0,"tweets":2956,"lists":2055,"mentionsReceived":2131233,"retweetsReceived":934711,"followersFollowing":0},{"timestamp":1673774280,"date":"2023-01-15","followers":5877693,"following":0,"tweets":2959,"lists":2062,"mentionsReceived":2148673,"retweetsReceived":936774,"followersFollowing":0},{"timestamp":1676366280,"date":"2023-02-14","followers":5909298,"following":0,"tweets":2961,"lists":2067,"mentionsReceived":2169057,"retweetsReceived":938210,"followersFollowing":0},{"timestamp":1678958280,"date":"2023-03-16","followers":5917368,"following":0,"tweets":2961,"lists":2076,"mentionsReceived":2182152,"retweetsReceived":938311,"followersFollowing":0},{"timestamp":1681550280,"date":"2023-04-15","followers":5935260,"following":0,"tweets":2967,"lists":2085,"mentionsReceived":2202153,"retweetsReceived":942276,"followersFollowing":0},{"timestamp":1684142280,"date":"2023-05-15","followers":5944056,"following":0,"tweets":2970,"lists":2096,"mentionsReceived":2218160,"retweetsReceived":943516,"followersFollowing":0},{"timestamp":1686734280,"date":"2023-06-14","followers":5955686,"following":0,"tweets":2970,"lists":2102,"mentionsReceived":2234549,"retweetsReceived":943614,"followersFollowing":0},{"timestamp":1689326280,"date":"2023-07-14","followers":5964063,"following":0,"tweets":2974,"lists":2120,"mentionsReceived":2258402,"retweetsReceived":946190,"followersFollowing":0},{"timestamp":1691918280,"date":"2023-08-13","followers":5976784,"following":0,"tweets":2975,"lists":2117,"mentionsReceived":2278023,"retweetsReceived":946954,"followersFollowing":0},{"timestamp":1694510280,"date":"2023-09-12","followers":5984743,"following":0,"tweets":2979,"lists":2132,"mentionsReceived":2299316,"retweetsReceived":949317,"followersFollowing":0},{"timestamp":1697102280,"date":"2023-10-12","followers":6040175,"following":0,"tweets":2981,"lists":2153,"mentionsReceived":2332984,"retweetsReceived":954822,"followersFollowing":0},{"timestamp":1699694280,"date":"2023-11-11","followers":6089527,"following":0,"tweets":2980,"lists":2175,"mentionsReceived":2414182,"retweetsReceived":963882,"followersFollowing":0},{"timestamp":1702286280,"date":"2023-12-11","followers":6121334,"following":0,"tweets":2983,"lists":2190,"mentionsReceived":2488190,"retweetsReceived":969747,"followersFollowing":0},{"timestamp":1704878280,"date":"2024-01-10","followers":6132062,"following":0,"tweets":2981,"lists":2190,"mentionsReceived":2539354,"retweetsReceived":969888,"followersFollowing":0},{"timestamp":1707470280,"date":"2024-02-09","followers":6143232,"following":0,"tweets":2982,"lists":2200,"mentionsReceived":2604600,"retweetsReceived":972477,"followersFollowing":0},{"timestamp":1710062280,"date":"2024-03-10","followers":6155494,"following":0,"tweets":2982,"lists":2200,"mentionsReceived":2639302,"retweetsReceived":972806,"followersFollowing":0},{"timestamp":1712654280,"date":"2024-04-09","followers":6155603,"following":0,"tweets":2983,"lists":2205,"mentionsReceived":2678822,"retweetsReceived":973123,"followersFollowing":0},{"timestamp":1715246280,"date":"2024-05-09","followers":6171663,"following":0,"tweets":2989,"lists":2211,"mentionsReceived":2720664,"retweetsReceived":976501,"followersFollowing":0},{"timestamp":1717838280,"date":"2024-06-08","followers":6186006,"following":0,"tweets":2992,"lists":2222,"mentionsReceived":2768085,"retweetsReceived":982304,"followersFollowing":0},{"timestamp":1720430280,"date":"2024-07-08","followers":6194444,"following":0,"tweets":2993,"lists":2227,"mentionsReceived":2815963,"retweetsReceived":985952,"followersFollowing":0},{"timestamp":1723022280,"date":"2024-08-07","followers":6200888,"following":0,"tweets":2995,"lists":2225,"mentionsReceived":2845767,"retweetsReceived":986878,"followersFollowing":0},{"timestamp":1725614280,"date":"2024-09-06","followers":6208612,"following":0,"tweets":2996,"lists":2229,"mentionsReceived":2873677,"retweetsReceived":988532,"followersFollowing":0},{"timestamp":1728206280,"date":"2024-10-06","followers":6216802,"following":0,"tweets":2997,"lists":2233,"mentionsReceived":2900020,"retweetsReceived":991590,"followersFollowing":0},{"timestamp":1730798280,"date":"2024-11-05","followers":6227096,"following":0,"tweets":3002,"lists":2233,"mentionsReceived":2927116,"retweetsReceived":992118,"followersFollowing":0},{"timestamp":1733390280,"date":"2024-12-05","followers":6238063,"following":0,"tweets":3008,"lists":2242,"mentionsReceived":2966313,"retweetsReceived":995107,"followersFollowing":0},{"timestamp":1735982280,"date":"2025-01-04","followers":6250482,"following":0,"tweets":3014,"lists":2257,"mentionsReceived":3002803,"retweetsReceived":998458,"followersFollowing":0},{"timestamp":1738574280,"date":"2025-02-03","followers":6269951,"following":0,"tweets":3022,"lists":2299,"mentionsReceived":3046997,"retweetsReceived":1006615,"followersFollowing":0},{"timestamp":1741166280,"date":"2025-03-05","followers":6281017,"following":0,"tweets":3027,"lists":2307,"mentionsReceived":3080915,"retweetsReceived":1011745,"followersFollowing":0},{"timestamp":1743758280,"date":"2025-04-04","followers":6288204,"following":0,"tweets":3033,"lists":2317,"mentionsReceived":3119472,"retweetsReceived":1018117,"followersFollowing":0},{"timestamp":1746350280,"date":"2025-05-04","followers":6291923,"following":0,"tweets":3036,"lists":2328,"mentionsReceived":3150692,"retweetsReceived":1020217,"followersFollowing":0},{"timestamp":1748942280,"date":"2025-06-03","followers":6307249,"following":0,"tweets":3040,"lists":2338,"mentionsReceived":3182652,"retweetsReceived":1022329,"followersFollowing":0},{"timestamp":1751534280,"date":"2025-07-03","followers":6321390,"following":0,"tweets":3045,"lists":2342,"mentionsReceived":3236345,"retweetsReceived":1025650,"followersFollowing":0},{"timestamp":1754126280,"date":"2025-08-02","followers":6333009,"following":0,"tweets":3046,"lists":2349,"mentionsReceived":3286857,"retweetsReceived":1028873,"followersFollowing":0},{"timestamp":1756718280,"date":"2025-09-01","followers":6341642,"following":0,"tweets":3055,"lists":2364,"mentionsReceived":3322074,"retweetsReceived":1030033,"followersFollowing":0},{"timestamp":1759310280,"date":"2025-10-01","followers":6336005,"following":0,"tweets":3058,"lists":2360,"mentionsReceived":3359596,"retweetsReceived":1033017,"followersFollowing":0},{"timestamp":1761902280,"date":"2025-10-31","followers":6282304,"following":0,"tweets":3060,"lists":2350,"mentionsReceived":3408997,"retweetsReceived":1044954,"followersFollowing":0},{"timestamp":1764494280,"date":"2025-11-30","followers":6255694,"following":0,"tweets":3060,"lists":2337,"mentionsReceived":3436453,"retweetsReceived":1049631,"followersFollowing":0},{"timestamp":1767086280,"date":"2025-12-30","followers":6261752,"following":0,"tweets":3065,"lists":2338,"mentionsReceived":3451739,"retweetsReceived":1050237,"followersFollowing":0},{"timestamp":1769678280,"date":"2026-01-29","followers":6265516,"following":0,"tweets":3066,"lists":2340,"mentionsReceived":3474996,"retweetsReceived":1053797,"followersFollowing":0},{"timestamp":1772270280,"date":"2026-02-28","followers":6275209,"following":0,"tweets":3067,"lists":2339,"mentionsReceived":3500291,"retweetsReceived":1056194,"followersFollowing":0},{"timestamp":1777022280,"date":"2026-04-24","followers":6290179,"following":0,"tweets":3070,"lists":2337,"mentionsReceived":3530584,"retweetsReceived":1058587,"followersFollowing":0}],"fetchedAt":"2026-04-24T09:18:08.400Z"}}